pystructurebuilder/__init__.py
pystructurebuilder/pystructurebuilder.py
pystructurebuilder/utils.py
pystructurebuilder-1.0.3.dist-info/LICENSE
pystructurebuilder-1.0.3.dist-info/METADATA
pystructurebuilder-1.0.3.dist-info/WHEEL
pystructurebuilder-1.0.3.dist-info/top_level.txt
pystructurebuilder-1.0.3.dist-info/RECORD
