Metadata-Version: 2.1
Name: pystructurebuilder
Version: 1.0.3
Summary: A Python module to generate a detailed description of a project's directory structure.
Author-email: eis-x <eis-x@hotmail.com>
License: MIT License
Project-URL: Homepage, https://github.com/eis-x/pystructurebuilder
Classifier: Programming Language :: Python :: 3
Classifier: License :: OSI Approved :: MIT License
Classifier: Operating System :: OS Independent
Requires-Python: >=3.6
License-File: LICENSE
